{
  "input": "input.mp4",
  "output": "output.mp4",
  "width": 1280,
  "height": 720,
  "fps": 30,
  "subtitle": {
    "srt": "examples/sample.srt",
    "gaussian_blur": true,
    "font": "Noto Sans",
    "size": 48,
    "bold": true,
    "italic": false,
    "color": "#FFF200",
    "outline_color": "#101010",
    "back_color": "#00000000",
    "outline": 4,
    "shadow": 0,
    "margin": 12,
    "opacity": 1.0,
    "regions": [
      {
        "start": 1.2,
        "end": 4.8,
        "x": 0,
        "y": 610,
        "w": 1280,
        "h": 90,
        "strength": 0.9,
        "feather": 36,
        "vertical_stretch": 1.0,
        "horizontal_blur": 0.4,
        "temporal_blend": 0.12
      }
    ]
  },
  "watermark": {
    "text": "@hoanganhcoder",
    "font": "Noto Sans",
    "size": 30,
    "bold": true,
    "color": "#FFFFFF",
    "outline_color": "#000000",
    "back_color": "#00000000",
    "outline": 1,
    "shadow": 0,
    "margin": 28,
    "bounce": true,
    "speed_x": 88.0,
    "speed_y": 60.0,
    "opacity": 0.28
  },
  "logo": {
    "path": "logo.png",
    "scale": 0.16,
    "opacity": 0.24,
    "margin": 24,
    "bounce": false,
    "speed_x": 60.0,
    "speed_y": 42.0
  }
}
